IDRSolutions/IDRCloudClient.py
IDRSolutions/__init__.py
IDRCloudClient-5.0.1.dist-info/LICENSE.txt
IDRCloudClient-5.0.1.dist-info/METADATA
IDRCloudClient-5.0.1.dist-info/NOTICE.txt
IDRCloudClient-5.0.1.dist-info/WHEEL
IDRCloudClient-5.0.1.dist-info/top_level.txt
IDRCloudClient-5.0.1.dist-info/RECORD
