Metadata-Version: 2.1
Name: IDRCloudClient
Version: 5.0.1
Summary: Python API for IDRSolutions' Microservice Examples
Home-page: https://github.com/idrsolutions/IDRSolutions-python-client
Author: IDRSolutions
Author-email: support@idrsolutions.zendesk.com
License: Apache 2.0
Project-URL: Source, https://github.com/idrsolutions/IDRSolutions-python-client/
Project-URL: Tracker, https://github.com/idrsolutions/IDRSolutions-python-client/issues
Project-URL: Contact us, https://idrsolutions.zendesk.com/hc/en-us/requests/new
Keywords: idrsolutions pdf html5 image converter buildvu jpedal microservice example web application server API python client
Classifier: Development Status :: 4 - Beta
Classifier: Intended Audience :: Developers
Classifier: Topic :: Software Development :: Libraries :: Python Modules
Classifier: License :: OSI Approved :: Apache Software License
Classifier: Programming Language :: Python :: 3 :: Only
License-File: LICENSE.txt
License-File: NOTICE.txt
Requires-Dist: requests
